boomdiff/__init__.py
boomdiff/autodiff.py
boomdiff/loss_function.py
boomdiff/ad/__init__.py
boomdiff/ad/autodiff.py
boomdiff/boomdiff_ad/__init__.py
boomdiff/boomdiff_ad/autodiff.py
boomdiff/boomdiff_optimize/__init__.py
boomdiff/optimize/__init__.py
boomdiff/optimize/_adam.py
boomdiff/optimize/_gradient_descent.py
boomdiff/optimize/_momentum.py
boomdiff/optimize/_optimizer.py
boomdiff/optimize/gradient_descent.py
boomdiff/optimize/optimizer.py
tests/__init__.py
tests/test_arrays.py
tests/test_loss_functions.py
tests/test_optimizer.py
tests/test_suite.py
tests/test_unit.py
boomdiff-2.0.dist-info/LICENSE.txt
boomdiff-2.0.dist-info/METADATA
boomdiff-2.0.dist-info/WHEEL
boomdiff-2.0.dist-info/top_level.txt
boomdiff-2.0.dist-info/RECORD
