Metadata-Version: 2.1
Name: boomdiff
Version: 2.0
Summary: Optimizes user-specified objective functions of many variables using gradient-based optimization; relies on autodifferentiation for fast computation of gradients.
Home-page: https://github.com/team-boomeraang/cs107-FinalProject
Author: Minhaun Li, Oksana Makarova, Timothy Williamson, Kevin Hare
Author-email: UNKNOWN
License: UNKNOWN
Platform: UNKNOWN
Requires-Dist: numpy
Requires-Dist: matplotlib
